snowfinch/__init__.py
snowfinch/ansi.py
snowfinch/cli.py
snowfinch/compat.py
snowfinch/connections.py
snowfinch/constants.py
snowfinch/encrypt.py
snowfinch/exceptions.py
snowfinch/fincher.py
snowfinch/fs.py
snowfinch/log.py
snowfinch/logger.py
snowfinch/sf2s3.py
snowfinch/sfconnect.py
snowfinch/shell.py
snowfinch/sshclient.py
snowfinch/td2s3.py
snowfinch/utils.py
snowfinch/aws/__init__.py
snowfinch/aws/s3.py
snowfinch/aws/s3upload.py
snowfinch/aws/s3utils.py
snowfinch/aws/secrets.py
snowfinch/parsers/__init__.py
snowfinch/parsers/bteqparser.py
snowfinch/parsers/commons.py
snowfinch/parsers/ddl_generators.py
snowfinch/parsers/ddlparser.py
snowfinch/parsers/mssql_parser.py
snowfinch/parsers/parser.py
snowfinch/parsers/sproc_parser.py
snowfinch-0.1.dev15.dist-info/AUTHORS.rst
snowfinch-0.1.dev15.dist-info/LICENSE.txt
snowfinch-0.1.dev15.dist-info/METADATA
snowfinch-0.1.dev15.dist-info/WHEEL
snowfinch-0.1.dev15.dist-info/entry_points.txt
snowfinch-0.1.dev15.dist-info/top_level.txt
snowfinch-0.1.dev15.dist-info/RECORD
