Metadata-Version: 2.1
Name: snowfinch
Version: 0.1.dev15
Summary: A framework to migrate sql objects to snowflake from different databases
Home-page: https://bitbucket.anthem.com/users/ag29266/repos/snowfinch
Author: Kadam, Gangadhar
Author-email: gangadhar.kadam@anthem.com
License: MIT
Project-URL: Documentation, https://snowfinch.readthedocs.io/
Project-URL: Release Notes, https://snowfinch.readthedocs.io/en/latest/changes/
Project-URL: source, https://bitbucket.anthem.com/users/ag29266/repos/snowfinch
Project-URL: Tracker, https://bitbucket.anthem.com/users/ag29266/repos/snowfinch/issues
Platform: any
Classifier: Development Status :: 3 - Alpha
Classifier: Intended Audience :: Developers
Classifier: Topic :: Software Development
Classifier: Topic :: Database
Classifier: License :: OSI Approved :: MIT License
Classifier: Operating System :: OS Independent
Classifier: Programming Language :: Python
Classifier: Programming Language :: Python :: 3
Classifier: Programming Language :: Python :: 3.7
Classifier: Programming Language :: Python :: 3.8
Requires-Python: >=3.6
License-File: LICENSE.txt
License-File: AUTHORS.rst
Requires-Dist: importlib-metadata
Requires-Dist: sqlalchemy (~=1.4.17)
Requires-Dist: sqlalchemy-teradata
Requires-Dist: teradatasqlalchemy
Requires-Dist: snowflake (~=0.0.3)
Requires-Dist: snowflake-sqlalchemy
Requires-Dist: snowflake-connector-python (~=2.5.1)
Requires-Dist: numpy (~=1.20.3)
Requires-Dist: pandas (~=1.2.4)
Requires-Dist: pyodbc (~=4.0.30)
Requires-Dist: sqlalchemy-pyodbc-mssql
Requires-Dist: teradatasql (==17.10.0.1)
Requires-Dist: teradata (~=15.10.0.21)
Requires-Dist: setuptools (~=57.0.0)
Requires-Dist: confuse (~=1.4.0)
Requires-Dist: PyYAML (~=5.4.1)
Requires-Dist: pymssql (~=2.2.1)
Requires-Dist: attrs
Requires-Dist: boto3 (~=1.17.87)
Requires-Dist: botocore (~=1.20.87)
Requires-Dist: sqlparse (~=0.4.1)
Requires-Dist: PyMySQL (~=1.0.2)
Requires-Dist: python-dateutil (~=2.8.1)
Requires-Dist: requests (>=1.2.0)
Requires-Dist: futures (>=2.1.3)
Requires-Dist: pyfiglet (~=0.8.post1)
Requires-Dist: python-json-logger (==2.0.0)
Requires-Dist: colorama (~=0.4.4)
Requires-Dist: boto (~=2.49.0)
Requires-Dist: ddlparse (~=1.9.0)
Requires-Dist: pyparsing (~=2.4.7)
Requires-Dist: crypto (~=1.4.1)
Requires-Dist: pytool (~=3.16.1)
Requires-Dist: paramiko (~=2.7.2)
Requires-Dist: scp (~=0.13.6)
Requires-Dist: dynaconf (~=3.1.4)
